{"kind":"identitytoolkit#DownloadAccountResponse","users":[{"localId":"SQd2GveBL76UInd4PQmk6HWmoIJK","createdAt":"1652714894023","lastLoginAt":"1652714894022","displayName":"John Doe","photoUrl":"","emailVerified":false,"email":"jd@gmail.com","salt":"fakeSaltl18cxNyJawYHVGOK3RAb","passwordHash":"fakeHash:salt=fakeSaltl18cxNyJawYHVGOK3RAb:password=password","passwordUpdatedAt":1652714894023,"validSince":"1652714894","providerUserInfo":[{"providerId":"password","email":"jd@gmail.com","federatedId":"jd@gmail.com","rawId":"jd@gmail.com","displayName":"John Doe","photoUrl":""}]}]}